[{
    "name": "yoruka",
    "fullName": "須多夜花",
    "fullConfigURL": "assets/configs/yoruka.json",
    "liveUpdateURL": "https://soundbuttons.blob.core.windows.net/sound-buttons/yoruka/yoruka.json",
    "imgSrc": "https://soundbuttons.blob.core.windows.net/sound-buttons/yoruka/yoruka.png",
    "color": {
      "primary": "#33272B",
      "secondary": "#E55A74"
    }
  }, {
    "name": "tama",
    "fullName": "久遠たま",
    "fullConfigURL": "assets/configs/tama.json",
    "liveUpdateURL": "https://soundbuttons.blob.core.windows.net/sound-buttons/tama/tama.json",
    "imgSrc": "https://soundbuttons.blob.core.windows.net/sound-buttons/tama/tama.png",
    "color": {
      "primary": "#593196",
      "secondary": "#a991d4"
    }
  },
  {
    "name": "kakeru",
    "fullName": "間取かける",
    "fullConfigURL": "assets/configs/kakeru.json",
    "liveUpdateURL": "https://soundbuttons.blob.core.windows.net/sound-buttons/kakeru/kakeru.json",
    "imgSrc": "https://soundbuttons.blob.core.windows.net/sound-buttons/kakeru/kakeru.png",
    "color": {
      "primary": "#2C252C",
      "secondary": "#F9D95E"
    }
  },
  {
    "name": "emurii",
    "fullName": "苓吃エムリィ",
    "fullConfigURL": "assets/configs/emurii.json",
    "liveUpdateURL": "https://soundbuttons.blob.core.windows.net/sound-buttons/emurii/emurii.json",
    "imgSrc": "https://soundbuttons.blob.core.windows.net/sound-buttons/emurii/emurii.png",
    "color": {
      "primary": "#B933F8",
      "secondary": "#DEC5E5"
    }
  },
  {
    "name": "aruma",
    "fullName": "薬袋アルマ",
    "fullConfigURL": "assets/configs/aruma.json",
    "liveUpdateURL": "https://soundbuttons.blob.core.windows.net/sound-buttons/aruma/aruma.json",
    "imgSrc": "https://soundbuttons.blob.core.windows.net/sound-buttons/aruma/aruma.png",
    "color": {
      "primary": "#2A5CAB",
      "secondary": "#B3CEF0"
    }
  }
]
